README.md
setup.py
database/__init__.py
database/database.py
database/fields.py
gyver_database.egg-info/PKG-INFO
gyver_database.egg-info/SOURCES.txt
gyver_database.egg-info/dependency_links.txt
gyver_database.egg-info/top_level.txt