Metadata-Version: 2.1
Name: gyver-database
Version: 0.5.0
Summary: UNKNOWN
Home-page: https://github.com/MaxGyverTech/database/
Author: MaxGyverTech
Author-email: maksimfadeenko2@gmail.com
License: UNKNOWN
Platform: UNKNOWN
Classifier: Programming Language :: Python :: 3
Classifier: License :: OSI Approved :: MIT License
Classifier: Operating System :: OS Independent
Requires-Python: >=3.8
